Metadata-Version: 2.1
Name: django-admin-data-export
Version: 1.0.14
Summary: A comprehensive Django app that enhances the admin interface with advanced export functionality for CSV, Excel, and JSON formats.
Home-page: https://github.com/NyuydineBill/data2csv
Author: Nyuydine Bill
Author-email: billleynyuy@gmail.com
License: MIT
Project-URL: Bug Reports, https://github.com/NyuydineBill/data2csv/issues
Project-URL: Source, https://github.com/NyuydineBill/data2csv
Project-URL: Documentation, https://github.com/NyuydineBill/data2csv#readme
Keywords: django admin export csv excel json data
Platform: UNKNOWN
Classifier: Development Status :: 4 - Beta
Classifier: Environment :: Web Environment
Classifier: Framework :: Django
Classifier: Framework :: Django :: 3.2
Classifier: Framework :: Django :: 4.0
Classifier: Framework :: Django :: 4.1
Classifier: Framework :: Django :: 4.2
Classifier: Framework :: Django :: 5.0
Classifier: Intended Audience :: Developers
Classifier: License :: OSI Approved :: MIT License
Classifier: Operating System :: OS Independent
Classifier: Programming Language :: Python
Classifier: Programming Language :: Python :: 3
Classifier: Programming Language :: Python :: 3.8
Classifier: Programming Language :: Python :: 3.9
Classifier: Programming Language :: Python :: 3.10
Classifier: Programming Language :: Python :: 3.11
Classifier: Programming Language :: Python :: 3.12
Classifier: Topic :: Software Development :: Libraries :: Python Modules
Classifier: Topic :: Office/Business :: Financial :: Spreadsheet
Classifier: Topic :: Scientific/Engineering :: Information Analysis
Requires-Python: >=3.8
Requires-Dist: Django>=3.2
Requires-Dist: openpyxl>=3.0.7
Provides-Extra: dev
Requires-Dist: black>=22.0; extra == "dev"
Requires-Dist: flake8>=4.0; extra == "dev"
Requires-Dist: isort>=5.0; extra == "dev"
Requires-Dist: pytest-django>=4.0; extra == "dev"
Requires-Dist: pytest>=6.0; extra == "dev"
Provides-Extra: docs
Requires-Dist: Sphinx>=4.0; extra == "docs"
Requires-Dist: sphinx-rtd-theme>=1.0; extra == "docs"
